simplesheetsapi/SheetsApi.py
simplesheetsapi/__init__.py
simplesheetsapi-0.0.9.dist-info/LICENCE
simplesheetsapi-0.0.9.dist-info/METADATA
simplesheetsapi-0.0.9.dist-info/WHEEL
simplesheetsapi-0.0.9.dist-info/top_level.txt
simplesheetsapi-0.0.9.dist-info/RECORD
