Metadata-Version: 2.1
Name: simplesheetsapi
Version: 0.0.9
Summary: A small example package
Author-email: Sheets Try <sheetsapitry@gmail.com>
Classifier: Programming Language :: Python :: 3
Classifier: License :: OSI Approved :: MIT License
Classifier: Operating System :: OS Independent
Requires-Python: >=3.7
License-File: LICENCE
